<?xml version="1.0" encoding="utf-8"?>
<edmx:Edmx Version="1.0" xmlns:edmx="http://schemas.microsoft.com/ado/2007/06/edmx" xmlns:m="http://schemas.microsoft.com/ado/2007/08/dataservices/metadata" xmlns:sap="http://www.sap.com/Protocols/SAPData">
    <edmx:DataServices m:DataServiceVersion="2.0">
        <Schema Namespace="Z03_024_FFINANCE_01_SRV" xml:lang="en" sap:schema-version="1" xmlns="http://schemas.microsoft.com/ado/2008/09/edm">
            <EntityType Name="Finance" sap:content-version="1">
                <Key>
                    <PropertyRef Name="FiscalYear"/>
                </Key>
                <Property Name="FiscalYear" Type="Edm.Int16" Nullable="false" sap:unicode="false" sap:label="YEAR" sap:updatable="false" sap:sortable="false"/>
                <Property Name="ClubExpense" Type="Edm.Int32" Nullable="false" sap:unicode="false" sap:label="Chi Phi" sap:sortable="false" sap:filterable="false"/>
                <Property Name="ClubIncome" Type="Edm.Int32" Nullable="false" sap:unicode="false" sap:label="Thu Nhap" sap:sortable="false" sap:filterable="false"/>
            </EntityType>
            <EntityContainer Name="Z03_024_FFINANCE_01_SRV_Entities" m:IsDefaultEntityContainer="true" sap:supported-formats="atom json xlsx">
                <EntitySet Name="Finances" EntityType="Z03_024_FFINANCE_01_SRV.Finance" sap:pageable="false" sap:addressable="false" sap:content-version="1"/>
            </EntityContainer>
            <atom:link rel="self" href="https://s72lp1.ucc.in.tum.de:8100/sap/opu/odata/sap/Z03_024_FFINANCE_01_SRV/$metadata" xmlns:atom="http://www.w3.org/2005/Atom"/>
            <atom:link rel="latest-version" href="https://s72lp1.ucc.in.tum.de:8100/sap/opu/odata/sap/Z03_024_FFINANCE_01_SRV/$metadata" xmlns:atom="http://www.w3.org/2005/Atom"/>
        </Schema>
    </edmx:DataServices>
</edmx:Edmx>